HeadlessPywhatKit/__init__.py
HeadlessPywhatKit/app.py
HeadlessPywhatKit/whats.py
HeadLessPywhatKit-0.0.5.dist-info/LICENSE
HeadLessPywhatKit-0.0.5.dist-info/METADATA
HeadLessPywhatKit-0.0.5.dist-info/WHEEL
HeadLessPywhatKit-0.0.5.dist-info/top_level.txt
HeadLessPywhatKit-0.0.5.dist-info/RECORD
