Metadata-Version: 2.1
Name: HeadLessPywhatKit
Version: 0.0.5
Summary: This is the headless Version Of pywhatKit
Home-page: https://github.com/SigireddyBalasai/HeadlessAsyncPywhatKit
Author: SigireddyBalasai
Author-email: SigireddyBalasai@gmail.com
License: Apache 2.0
Keywords: sendwhatmsg
Classifier: Development Status :: 5 - Production/Stable
Classifier: Intended Audience :: Developers
Classifier: Topic :: Software Development :: Build Tools
Classifier: License :: OSI Approved :: MIT License
Classifier: Programming Language :: Python :: 3.8
Classifier: Programming Language :: Python :: 3.9
Classifier: Programming Language :: Python :: 3.10
License-File: LICENSE
Requires-Dist: selenium (~=4.7)
Requires-Dist: setuptools (==65.6.3)
Requires-Dist: Flask (~=2.2.2)
Requires-Dist: requests (~=2.28.1)
